charms/unit_test.py
charms.unit_test-1.1.2.dist-info/METADATA
charms.unit_test-1.1.2.dist-info/WHEEL
charms.unit_test-1.1.2.dist-info/top_level.txt
charms.unit_test-1.1.2.dist-info/RECORD
