Metadata-Version: 2.1
Name: charms.unit-test
Version: 1.1.2
Summary: Helpers for unit-testing reactive-style Juju Charms
Home-page: https://github.com/juju-solutions/charms.unit_test
Author: Cory Johns
Author-email: johnsca@gmail.com
License: Apache License 2.0
Requires-Dist: pytest
